etyping/__init__.py
etyping/_constants.py
etyping/_site.py
etyping/category.py
etyping/cli.py
etyping/game.py
etyping/webdriver.py
etyping-2.0.0.dist-info/entry_points.txt
etyping-2.0.0.dist-info/LICENSE
etyping-2.0.0.dist-info/WHEEL
etyping-2.0.0.dist-info/METADATA
etyping-2.0.0.dist-info/RECORD
